aidoc.py
aidoc-0.1.5.dist-info/LICENSE
aidoc-0.1.5.dist-info/METADATA
aidoc-0.1.5.dist-info/WHEEL
aidoc-0.1.5.dist-info/entry_points.txt
aidoc-0.1.5.dist-info/top_level.txt
aidoc-0.1.5.dist-info/RECORD
