Metadata-Version: 2.1
Name: aidoc
Version: 0.1.5
Summary: A simple CLI tool to generate documentation for your Python projects automatically.
Home-page: https://github.com/saikatkumardey/aidoc
Author: Saikat Kumar Dey
Author-email: deysaikatkumar@gmail.com
Classifier: Programming Language :: Python :: 3
Classifier: License :: OSI Approved :: GNU General Public License v3 or later (GPLv3+)
Classifier: Operating System :: OS Independent
Requires-Python: >=3.6
License-File: LICENSE
Requires-Dist: astor (==0.8.1)
Requires-Dist: black (==22.12.0)
Requires-Dist: openai (==0.25.0)
Requires-Dist: python-dotenv (==0.21.0)
Requires-Dist: setuptools (==65.6.3)
